Checkpointing/ChkptDescFileGen/smpt2ckptdesc.py
Checkpointing/DumpHTIF/chkpt_htif_dump.py
CpuTraceAnalysis/ignore_symbol.yaml
CpuTraceAnalysis/libcputrace/MachineCode/CppDemangler.py
CpuTraceAnalysis/libcputrace/MachineCode/Instruction.py
CpuTraceAnalysis/libcputrace/MachineCode/Label.py
CpuTraceAnalysis/libcputrace/MachineCode/Objdump.py
CpuTraceAnalysis/libcputrace/MachineCode/SymbolTable.py
CpuTraceAnalysis/libcputrace/MachineCode/__init__.py
CpuTraceAnalysis/libcputrace/StackAnalysis/CallStackTracker.py
CpuTraceAnalysis/libcputrace/StackAnalysis/HistoryRecorder.py
CpuTraceAnalysis/libcputrace/StackAnalysis/Recorder/GoogleTraceEventFormatRecorder.py
CpuTraceAnalysis/libcputrace/StackAnalysis/Recorder/JsonHistoryRecorder.py
CpuTraceAnalysis/libcputrace/StackAnalysis/Recorder/__init__.py
CpuTraceAnalysis/libcputrace/StackAnalysis/TraceCodePatternScanner.py
CpuTraceAnalysis/libcputrace/StackAnalysis/__init__.py
CpuTraceAnalysis/libcputrace/Trace/SimpleTraceFileReader.py
CpuTraceAnalysis/libcputrace/Trace/TraceEvent.py
CpuTraceAnalysis/libcputrace/Trace/__init__.py
CpuTraceAnalysis/libcputrace/__init__.py
CpuTraceAnalysis/libcputrace/utils.py
CpuTraceAnalysis/symbol_query.py
CpuTraceAnalysis/trace2google.py
CpuTraceAnalysis/trace2tracevis.py
CpuTraceAnalysis/trace_diff.py
CpuTraceAnalysis/trace_seq_check.py
CpuTraceAnalysis/trace_vis/node_modules/vis-timeline/HISTORY.md
CpuTraceAnalysis/trace_vis/node_modules/vis-timeline/LICENSE.Apache-2.0.txt
CpuTraceAnalysis/trace_vis/node_modules/vis-timeline/LICENSE.MIT.txt
CpuTraceAnalysis/trace_vis/node_modules/vis-timeline/LICENSE.md
CpuTraceAnalysis/trace_vis/node_modules/vis-timeline/README.md
CpuTraceAnalysis/trace_vis/node_modules/vis-timeline/declarations/entry-esnext.d.ts
CpuTraceAnalysis/trace_vis/node_modules/vis-timeline/declarations/entry-peer.d.ts
CpuTraceAnalysis/trace_vis/node_modules/vis-timeline/declarations/entry-standalone.d.ts
CpuTraceAnalysis/trace_vis/node_modules/vis-timeline/declarations/index.d.ts
anycore_dbg_supplement-0.7.1.dist-info/LICENSE
anycore_dbg_supplement-0.7.1.dist-info/METADATA
anycore_dbg_supplement-0.7.1.dist-info/WHEEL
anycore_dbg_supplement-0.7.1.dist-info/entry_points.txt
anycore_dbg_supplement-0.7.1.dist-info/RECORD
