Metadata-Version: 2.3
Name: anycore-dbg-supplement
Version: 0.7.1
Summary: A bundle of auxiliary scripts for the Anycore project
License: Other/Proprietary License
Keywords: anycore
Author: Jiayang Li
Author-email: jli95@ncsu.edu
Requires-Python: >=3.9,<4.0
Classifier: Development Status :: 3 - Alpha
Classifier: License :: Other/Proprietary License
Classifier: Operating System :: POSIX :: Linux
Classifier: Programming Language :: Python :: 3
Classifier: Programming Language :: Python :: 3.9
Classifier: Programming Language :: Python :: 3.10
Classifier: Programming Language :: Python :: 3.11
Classifier: Programming Language :: Python :: 3.12
Classifier: Programming Language :: Python :: 3.13
Requires-Dist: PyYAML (>=6.0.2,<7.0.0)
Requires-Dist: bashlex (>=0.18,<0.19)
Requires-Dist: click (>=8.1.8,<9.0.0)
Requires-Dist: fuzzywuzzy (>=0.18.0,<0.19.0)
Requires-Dist: levenshtein (>=0.27.1,<0.28.0)
Requires-Dist: natsort (>=8.4.0,<9.0.0)
Requires-Dist: pyparsing (>=3.2.3,<4.0.0)
Project-URL: Repository, https://github.com/s117/anycore-dbg-supplement.git
